haplopy/__init__.py
haplopy/datautils.py
haplopy/multinomial.py
haplopy/plot.py
haplopy-0.1.3.dist-info/METADATA
haplopy-0.1.3.dist-info/WHEEL
haplopy-0.1.3.dist-info/top_level.txt
haplopy-0.1.3.dist-info/RECORD
