Metadata-Version: 2.1
Name: haplopy
Version: 0.1.3
Summary: Haplotype reconstruction from unphased diplotypes
Home-page: https://github.com/malmgrek/haplopy
Author: Stratos Staboulis <stratos@stratokraft.fi>
Maintainer: Stratos Staboulis <stratos@stratokraft.fi>
License: MIT
Keywords: statistics,modeling,population genetics
Classifier: Programming Language :: Python :: 3
Classifier: Development Status :: 3 - Alpha
Classifier: Intended Audience :: Science/Research
Classifier: Topic :: Scientific/Engineering :: Bio-Informatics
Classifier: License :: OSI Approved :: MIT License
Classifier: Operating System :: OS Independent
Requires-Dist: numpy (>=1.10.0)
Requires-Dist: scipy (>=0.13.0)
Provides-Extra: dev
Requires-Dist: matplotlib ; extra == 'dev'
Requires-Dist: ipython ; extra == 'dev'
Provides-Extra: test
Requires-Dist: pytest ; extra == 'test'
